{
  "slug": "planetono",
  "awwwards_url": "https://www.awwwards.com/sites/planetono",
  "live_url": "https://www.planetono.space",
  "title": "Planetoño",
  "agency": "Tubik",
  "agency_url": "https://www.awwwards.com/tubik/",
  "tags": [
    "Food & Drink",
    "Illustration",
    "Sound-Audio",
    "GSAP",
    "Three.js",
    "3D",
    "Interaction Design",
    "Blender"
  ],
  "award_tags": [
    "dev",
    "sotd"
  ],
  "award_date": "Mar 14, 2026",
  "created_at": 1773446400,
  "category": "SOTD",
  "thumbnail": "https://assets.awwwards.com/awards/media/cache/thumb_440_330/submissions/2026/02/6989b192c2c00454343328.png",
  "rank": 33,
  "fetched_at": 1776287816,
  "content_type": "text/html;charset=utf-8",
  "http_status": 200,
  "html_bytes": 147039,
  "stylesheets": [
    {
      "url": "https://www.planetono.space/_nuxt/entry.xOEq5fYY.css",
      "status": 200,
      "file": "__nuxt_entry.xOEq5fYY.css",
      "bytes": 22627
    },
    {
      "url": "https://www.planetono.space/_nuxt/RichText.22vVeUUE.css",
      "status": 200,
      "file": "__nuxt_RichText.22vVeUUE.css",
      "bytes": 23
    }
  ]
}