{
  "slug": "the-renaissance-edition",
  "awwwards_url": "https://www.awwwards.com/sites/the-renaissance-edition",
  "live_url": "https://www.shopify.com/editions/winter2026",
  "title": "The Renaissance Edition",
  "agency": "Shopify Design",
  "agency_url": "https://www.awwwards.com/shopifydesign/",
  "tags": [
    "E-Commerce",
    "Technology",
    "Web & Interactive",
    "Animation",
    "Parallax",
    "WebGL",
    "Transitions",
    "Shopify",
    "3D",
    "Gestures / Interaction",
    "Interaction Design",
    "Blender"
  ],
  "award_tags": [
    "ah",
    "dev",
    "sotm"
  ],
  "award_date": "",
  "created_at": 1770595200,
  "category": "SOTD",
  "thumbnail": "https://assets.awwwards.com/awards/media/cache/thumb_440_330/submissions/2025/12/6940bd028333f875677215.jpg",
  "rank": 66,
  "fetched_at": 1776287826,
  "content_type": "text/html",
  "http_status": 200,
  "html_bytes": 1450950,
  "stylesheets": []
}